<?xml version="1.0" encoding="UTF-8"?>
<stuff>
    <rubric>kniga glagolemaja granograf jaže sut' v nkze (= v knize) se rekše k načalo pismenom"
        carskich darov ot mnogich lětopisec" prežde o bytii o sotvorenii mira ot knig" moiseovych i
        ot isusa navina i ot sudei ijudeiskich i ot četyrech carstv" taže i ot asiriskich carech.
        Ellin že blagočestivych i ot ruskich lětopisec serbskich" i bolgarskich" pervee z bogom"
        počinaem o šestich dnech v nichže sotvoril vsju tvar' napisano ot premudrago manasija i ot
        sivirija episkopa geval"skago</rubric>
    <incipit>začalo 1:go dni v načale sotvori bog" nebo i zemlju.</incipit>
    <explicit>i mnogolětno zdravstvovati i vo vsjakom blagodenstvii i mužestvě i radosti vo věki
        amin.</explicit>
    <colophon>jazyk čelovečeskich 72 četveronogago rodu 54 rybja rodu 104 zmiina rodu 104</colophon>
</stuff>
